{
  "Motor_Nerve_Conduction_Studies": [
    {
      "Nerve_Muscles": "Lt. Ulnar ADQ",
      "Stimulus_Site": "W",
      "Latency_ms": "2.5",
      "Distance_cm": "7.0",
      "Amplitude_mv": "7.0",
      "NCV_ms": "-"
    },
    {
      "Nerve_Muscles": "Lt. Peroneal TA",
      "Stimulus_Site": "D. KNEE",
      "Latency_ms": "2.7",
      "Distance_cm": "7.0",
      "Amplitude_mv": "0.9",
      "NCV_ms": "-"
    },
    {
      "Nerve_Muscles": "Right ulnar (ADQ)",
      "Stimulus_Site": null,
      "Latency_ms": null,
      "Distance_cm": null,
      "Amplitude_mv": null,
      "NCV_ms": null
    },
    {
      "Nerve_Muscles": "........",
      "Stimulus_Site": "Elbow",
      "Latency_ms": "6.8",
      "Distance_cm": "11.0",
      "Amplitude_mv": "0.9",
      "NCV_ms": "35.2"
    }
  ],
  "Sensory_Nerve_Conduction_Studies": [
    {
      "Nerve": "Rt. Radial",
      "Recording_Site": "Snuff Box",
      "Stimulation_Site": "Fore Arm",
      "Latency_ms": "2.0",
      "Distance_cm": "13.0",
      "Amplitude_uv": "26.4",
      "NCV_ms": "66.5"
    },
    {
      "Nerve": "Right sural",
      "Recording_Site": null,
      "Stimulation_Site": null,
      "Latency_ms": "normal peak latency",
      "Distance_cm": null,
      "Amplitude_uv": "normal SNAP amplitude",
      "NCV_ms": "normal conduction velocity"
    }
  ],
  "Electromyography": [
    {
      "Muscles": "right orbicularis oris (Orbi. Oris)",
      "Fibs": null,
      "Psw": null,
      "Others": null,
      "Amp": null,
      "Duration": null,
      "Polys": null,
      "Recruit": null,
      "Interference": null
    },
    {
      "Muscles": "Rt. O. Oris",
      "Fibs": "Nil",
      "Psw": "Nil",
      "Others": "None",
      "Amp": "Normal",
      "Duration": "Normal",
      "Polys": "No",
      "Recruit": "Normal",
      "Interference": "-"
    },
    {
      "Muscles": "Rt. TA",
      "Fibs": "+2",
      "Psw": "+2",
      "Others": "None",
      "Amp": "High",
      "Duration": "Long",
      "Polys": "Polyphasic",
      "Recruit": "RFR",
      "Interference": "Reduced"
    }
  ]
}