{
  "Motor_Nerve_Conduction_Studies": [
    {
      "Nerve_Muscles": "|Rt Ulnar",
      "Stimulus_Site": "NR",
      "Latency_ms": "NR",
      "Distance_cm": "NR",
      "Amplitude_mv": "| 14.0",
      "NCV_ms": "NR"
    },
    {
      "Nerve_Muscles": "Rt. Post. tibial AH",
      "Stimulus_Site": "Ankle",
      "Latency_ms": "4.3",
      "Distance_cm": "7.0",
      "Amplitude_mv": "3.7",
      "NCV_ms": "-"
    }
  ],
  "Sensory_Nerve_Conduction_Studies": [],
  "Electromyography": [
    {
      "Muscles": "right orbicularis oris (O.Oris)",
      "Fibs": null,
      "Psw": null,
      "Others": "normal spontaneous activity, with normal Motor Unit Action Potential (MUAPs)",
      "Amp": null,
      "Duration": null,
      "Polys": null,
      "Recruit": "normal recruitment",
      "Interference": "normal interference pattern"
    },
    {
      "Muscles": "right orbicularis oris (Orbi. Oris)",
      "Fibs": null,
      "Psw": null,
      "Others": null,
      "Amp": null,
      "Duration": null,
      "Polys": null,
      "Recruit": null,
      "Interference": null
    },
    {
      "Muscles": "left first dorsal interosseous (FDI) and extensor digitorum communis (EDC)",
      "Fibs": "N/A",
      "Psw": "N/A",
      "Others": "normal spontaneous activity, with neurogenic Motor Unit Action Potential (MUAPs), rapid firing rate (RFR) recruitment",
      "Amp": "N/A",
      "Duration": "N/A",
      "Polys": "N/A",
      "Recruit": "N/A",
      "Interference": "reduced interference pattern"
    }
  ]
}