{
  "Motor_Nerve_Conduction_Studies": [
    {
      "Nerve_Muscles": "Bilateral posterior tibial (AH)",
      "Stimulus_Site": "N/A",
      "Latency_ms": "normal distal latencies",
      "Distance_cm": "N/A",
      "Amplitude_mv": "normal CMAP amplitudes",
      "NCV_ms": "slow conduction velocities"
    },
    {
      "Nerve_Muscles": "ee 6 SPSS ORD S Se ST ea SES CT Sk OS RE I Pi Sa",
      "Stimulus_Site": "NR",
      "Latency_ms": "NR",
      "Distance_cm": "NR",
      "Amplitude_mv": "NR",
      "NCV_ms": "NR"
    },
    {
      "Nerve_Muscles": "Triceps",
      "Stimulus_Site": "Triceps",
      "Latency_ms": "NR",
      "Distance_cm": "NR",
      "Amplitude_mv": "NR",
      "NCV_ms": "NR"
    }
  ],
  "Sensory_Nerve_Conduction_Studies": [
    {
      "Nerve": "Right ulnar",
      "Recording_Site": null,
      "Stimulation_Site": "(F5)",
      "Latency_ms": null,
      "Distance_cm": null,
      "Amplitude_uv": null,
      "NCV_ms": null
    }
  ],
  "Electromyography": [
    {
      "Muscles": "right first dorsal interosseous (FDI), biceps, and tibialis anterior (TA)",
      "Fibs": null,
      "Psw": null,
      "Others": "active denervation activity, with neurogenic Motor Unit Action Potential (MUAPs)",
      "Amp": null,
      "Duration": null,
      "Polys": null,
      "Recruit": "rapid firing rate (RFR) recruitment",
      "Interference": "reduced interference pattern"
    },
    {
      "Muscles": "Lt. EDC",
      "Fibs": "Nil",
      "Psw": "Nil",
      "Others": "None",
      "Amp": "High",
      "Duration": "Long",
      "Polys": "No",
      "Recruit": "RFR",
      "Interference": "Reduced"
    },
    {
      "Muscles": "Lt. Gastroc",
      "Fibs": "+++",
      "Psw": "+++",
      "Others": "None",
      "Amp": "Normal",
      "Duration": "Normal",
      "Polys": "No",
      "Recruit": "RFR",
      "Interference": "Reduced"
    }
  ]
}