{
  "Motor_Nerve_Conduction_Studies": [
    {
      "Nerve_Muscles": "Rt. Post. tibial AH",
      "Stimulus_Site": "Ankle",
      "Latency_ms": "4.3",
      "Distance_cm": "7.0",
      "Amplitude_mv": "3.7",
      "NCV_ms": "-"
    },
    {
      "Nerve_Muscles": "'' '' '' '' ''",
      "Stimulus_Site": "ELBOW",
      "Latency_ms": "7.8",
      "Distance_cm": "20.0",
      "Amplitude_mv": "5.2",
      "NCV_ms": "55.9"
    },
    {
      "Nerve_Muscles": "Rt. Peroneal EDB",
      "Stimulus_Site": "DK",
      "Latency_ms": "9.8",
      "Distance_cm": "30.0",
      "Amplitude_mv": "3.2",
      "NCV_ms": "48.4"
    },
    {
      "Nerve_Muscles": "“ “ “ “ “",
      "Stimulus_Site": "D. ELBOW",
      "Latency_ms": "7.3",
      "Distance_cm": "21.0",
      "Amplitude_mv": "6.3",
      "NCV_ms": "52.8"
    }
  ],
  "Sensory_Nerve_Conduction_Studies": [
    {
      "Nerve": "Bilateral median",
      "Recording_Site": null,
      "Stimulation_Site": null,
      "Latency_ms": null,
      "Distance_cm": null,
      "Amplitude_uv": null,
      "NCV_ms": "were not recordable (NR)"
    },
    {
      "Nerve": "Right sural",
      "Recording_Site": "",
      "Stimulation_Site": "",
      "Latency_ms": "NR",
      "Distance_cm": "",
      "Amplitude_uv": "NR",
      "NCV_ms": "NR"
    },
    {
      "Nerve": "Rt. Radial",
      "Recording_Site": "Snuff Box",
      "Stimulation_Site": "Fore Arm",
      "Latency_ms": "2.0",
      "Distance_cm": "13.0",
      "Amplitude_uv": "26.4",
      "NCV_ms": "66.5"
    },
    {
      "Nerve": "Lt. Radial",
      "Recording_Site": "Snuff Box",
      "Stimulation_Site": "Fore Arm",
      "Latency_ms": "2.0",
      "Distance_cm": "13.0",
      "Amplitude_uv": "30.5",
      "NCV_ms": "66.5"
    },
    {
      "Nerve": "Rt. Median",
      "Recording_Site": "F2",
      "Stimulation_Site": "Wrist",
      "Latency_ms": "2.6",
      "Distance_cm": "14.0",
      "Amplitude_uv": "22.7",
      "NCV_ms": "54.6"
    }
  ],
  "Electromyography": [
    {
      "Muscles": "Lt. Gastroc",
      "Fibs": "Nil",
      "Psw": "Nil",
      "Others": "None",
      "Amp": "High",
      "Duration": "Long",
      "Polys": "No",
      "Recruit": "Normal",
      "Interference": "-"
    },
    {
      "Muscles": "right tibialis anterior (TA)",
      "Fibs": null,
      "Psw": null,
      "Others": "neurogenic Motor Unit Action Potential (MUAPs), rapid firing rate recruitment and reduced interference pattern",
      "Amp": null,
      "Duration": null,
      "Polys": null,
      "Recruit": null,
      "Interference": null
    },
    {
      "Muscles": "gastrocnemius",
      "Fibs": null,
      "Psw": null,
      "Others": "active denervation activity, with neurogenic Motor Unit Action Potential (MUAPs), rapid firing rate (RFR) recruitment and reduced interference pattern",
      "Amp": null,
      "Duration": null,
      "Polys": null,
      "Recruit": null,
      "Interference": null
    }
  ]
}