{
  "Motor_Nerve_Conduction_Studies": [
    {
      "Nerve_Muscles": "Lt. Ulnar ADQ",
      "Stimulus_Site": "W",
      "Latency_ms": "2.5",
      "Distance_cm": "7.0",
      "Amplitude_mv": "7.0",
      "NCV_ms": "-"
    },
    {
      "Nerve_Muscles": "Rt. Ulnar ADQ",
      "Stimulus_Site": "DE",
      "Latency_ms": "5.4",
      "Distance_cm": "21.0",
      "Amplitude_mv": "6.4",
      "NCV_ms": "68.4"
    },
    {
      "Nerve_Muscles": "Rt. Median APB",
      "Stimulus_Site": "W",
      "Latency_ms": "2.6",
      "Distance_cm": "7.0",
      "Amplitude_mv": "6.3",
      "NCV_ms": "-"
    }
  ],
  "Sensory_Nerve_Conduction_Studies": [
    {
      "Nerve": "Bilateral median (F2)",
      "Recording_Site": null,
      "Stimulation_Site": null,
      "Latency_ms": null,
      "Distance_cm": null,
      "Amplitude_uv": null,
      "NCV_ms": null
    },
    {
      "Nerve": "Rt. Sural",
      "Recording_Site": "Ankle",
      "Stimulation_Site": "Calf",
      "Latency_ms": "2.7",
      "Distance_cm": "14.0",
      "Amplitude_uv": "16.4",
      "NCV_ms": "51.5"
    }
  ],
  "Electromyography": []
}