{
  "Motor_Nerve_Conduction_Studies": [
    {
      "Nerve_Muscles": "Lt. Post. tibial AH",
      "Stimulus_Site": "KNEE",
      "Latency_ms": "13.9",
      "Distance_cm": "41.5",
      "Amplitude_mv": "4.3",
      "NCV_ms": "42.0"
    },
    {
      "Nerve_Muscles": "Lt. Ulnar ADQ",
      "Stimulus_Site": "PE",
      "Latency_ms": "7.3",
      "Distance_cm": "10.0",
      "Amplitude_mv": "7.0",
      "NCV_ms": "62.9"
    },
    {
      "Nerve_Muscles": "Rt. Post. tibial AH",
      "Stimulus_Site": "PE",
      "Latency_ms": "9.8",
      "Distance_cm": "10.0",
      "Amplitude_mv": "10.0",
      "NCV_ms": "48.9"
    },
    {
      "Nerve_Muscles": "'' '' '' '' ''",
      "Stimulus_Site": "ELBOW",
      "Latency_ms": "7.8",
      "Distance_cm": "20.0",
      "Amplitude_mv": "5.2",
      "NCV_ms": "55.9"
    },
    {
      "Nerve_Muscles": "Rt. Median APB",
      "Stimulus_Site": "E",
      "Latency_ms": "7.8",
      "Distance_cm": "23.0",
      "Amplitude_mv": "5.1",
      "NCV_ms": "54.7"
    },
    {
      "Nerve_Muscles": "Rt. Ulnar ADQ",
      "Stimulus_Site": "P. ELBOW",
      "Latency_ms": "8.3",
      "Distance_cm": "9.0",
      "Amplitude_mv": "4.3",
      "NCV_ms": "49.5"
    }
  ],
  "Sensory_Nerve_Conduction_Studies": [
    {
      "Nerve": "Right ulnar",
      "Recording_Site": "(F5)",
      "Stimulation_Site": "N/A",
      "Latency_ms": "normal peak latency",
      "Distance_cm": "N/A",
      "Amplitude_uv": "normal SNAP amplitude",
      "NCV_ms": "normal conduction velocity"
    },
    {
      "Nerve": "Bilateral ulnar (F5)",
      "Recording_Site": null,
      "Stimulation_Site": null,
      "Latency_ms": null,
      "Distance_cm": null,
      "Amplitude_uv": null,
      "NCV_ms": null
    }
  ],
  "Electromyography": [
    {
      "Muscles": "vastus lateralis (VL)",
      "Fibs": null,
      "Psw": null,
      "Others": "active denervation activity, with neurogenic Motor Unit Action Potential (MUAPs), rapid firing rate (RFR) recruitment and reduced interference pattern",
      "Amp": null,
      "Duration": null,
      "Polys": null,
      "Recruit": null,
      "Interference": null
    },
    {
      "Muscles": "right first dorsal interosseous (FDI)",
      "Fibs": null,
      "Psw": null,
      "Others": "no motor units record",
      "Amp": null,
      "Duration": null,
      "Polys": null,
      "Recruit": null,
      "Interference": null
    }
  ]
}