{
  "Motor_Nerve_Conduction_Studies": [
    {
      "Nerve_Muscles": "Right peroneal (EDB)",
      "Stimulus_Site": "N/A",
      "Latency_ms": "normal distal latency",
      "Distance_cm": "N/A",
      "Amplitude_mv": "low CMAP amplitude",
      "NCV_ms": "slow conduction velocity"
    },
    {
      "Nerve_Muscles": "Right posterior tibial (AH)",
      "Stimulus_Site": "N/A",
      "Latency_ms": "normal distal latency",
      "Distance_cm": "N/A",
      "Amplitude_mv": "low CMAP amplitude",
      "NCV_ms": "slow conduction velocity"
    },
    {
      "Nerve_Muscles": "Right median (APB)",
      "Stimulus_Site": "N/A",
      "Latency_ms": "normal distal latency",
      "Distance_cm": "N/A",
      "Amplitude_mv": "normal CMAP amplitude",
      "NCV_ms": "normal conduction velocity"
    },
    {
      "Nerve_Muscles": "Right ulnar (ADQ)",
      "Stimulus_Site": "N/A",
      "Latency_ms": "normal distal latency",
      "Distance_cm": "N/A",
      "Amplitude_mv": "normal CMAP amplitude",
      "NCV_ms": "normal conduction velocity"
    }
  ],
  "Sensory_Nerve_Conduction_Studies": [
    {
      "Nerve": "Right ulnar",
      "Recording_Site": "N/A",
      "Stimulation_Site": "F5",
      "Latency_ms": "normal peak latency",
      "Distance_cm": "N/A",
      "Amplitude_uv": "normal SNAP amplitude",
      "NCV_ms": "normal conduction velocity"
    },
    {
      "Nerve": "Right sural",
      "Recording_Site": "N/A",
      "Stimulation_Site": "N/A",
      "Latency_ms": "normal peak latency",
      "Distance_cm": "N/A",
      "Amplitude_uv": "normal SNAP amplitude",
      "NCV_ms": "normal conduction velocity"
    },
    {
      "Nerve": "Right median",
      "Recording_Site": "N/A",
      "Stimulation_Site": "F2",
      "Latency_ms": "normal peak latency",
      "Distance_cm": "N/A",
      "Amplitude_uv": "normal SNAP amplitude",
      "NCV_ms": "normal conduction velocity"
    }
  ],
  "Electromyography": [
    {
      "Muscles": "N/A",
      "Fibs": "N/A",
      "Psw": "N/A",
      "Others": "N/A",
      "Amp": "N/A",
      "Duration": "N/A",
      "Polys": "N/A",
      "Recruit": "N/A",
      "Interference": "N/A"
    }
  ]
}